[
    {
        "Case ID": "032147",
        "Different Crime": [
            {
                "Crime Name": "Immigration Offense",
                "Crime Type": "Economic_Crimes_or_Fraud-related_Offenses",
                "humanitarian_compassionate_considerations": [
                    "H&C application",
                    "children's best interests",
                    "inability to file PRRA"
                ],
                "judicial_authority": [
                    "Judicial review application under IRPA subsection 72(1)"
                ],
                "decision_outcome": [
                    "denied deferral request",
                    "Judicial review dismissed"
                ],
                "applicable_statute": [
                    "IRPA section 48",
                    "IRPA subsection 72(1)"
                ],
                "reasonableness_standard": [
                    "reasonable, justified, transparent, and within acceptable outcomes under the law"
                ],
                "child_best_interests": [
                    "children's best interests"
                ],
                "special_circumstances": [
                    "exceptional circumstances"
                ]
            }
        ]
    },
    {
        "Case ID": "015122",
        "Different Crime": [
            {
                "Crime Name": "Work Permit Refusal under Immigration and Refugee Protection Regulations",
                "Crime Type": "Immigration-related_Fraud_or_Misrepresentation",
                "humanitarian_and_compassionate_factors": [
                    "H&C application",
                    "establishment in Canada",
                    "family connections"
                ],
                "risk_assessment": [
                    "alleged risks upon return"
                ],
                "best_interests_of_children": [
                    "child's best interests"
                ],
                "decision_outcome": [
                    "Removal deferral denied",
                    "judicial review dismissed"
                ],
                "standard_of_review": [
                    "reasonableness standard"
                ]
            }
        ]
    },
    {
        "Case ID": "060246",
        "Different Crime": [
            {
                "Crime Name": "Sexual Harassment and Discrimination",
                "Crime Type": "others",
                "legal_basis": [
                    "s. 44(3)(b)(i) of the Canadian Human Rights Act",
                    "s. 18.1 of the Federal Court Act"
                ],
                "discretion_exercise": [
                    "CHRC's discretionary powers"
                ],
                "procedure_followed": [
                    "Judicial review application",
                    "motion to strike irrelevant affidavits"
                ],
                "decision_reasoning": [
                    "CHRC acted within its discretionary powers",
                    "followed procedural requirements"
                ],
                "evidence_presented": [
                    "Investigation Report",
                    "applicant failed to submit comments or evidence"
                ],
                "result_of_case": [
                    "Application for judicial review denied",
                    "CHRC’s decision upheld with costs awarded to respondents"
                ]
            }
        ]
    },
    {
        "Case ID": "003173",
        "Different Crime": [
            {
                "Crime Name": "Immigration Removal Decision",
                "Crime Type": "Immigration-related_Fraud_or_Misrepresentation",
                "humanitarian_and_compassionate_factors": [
                    "pending H&C application not imminent enough"
                ],
                "health_grounds_inadmissibility": [
                    "medical care in Mexico"
                ],
                "decision_outcome": [
                    "judicial review dismissed"
                ],
                "standard_of_review": [
                    "Officer's decision was reasonable"
                ],
                "procedural_fairness": [
                    "consider medical accessibility and pending H&C applications"
                ]
            }
        ]
    },
    {
        "Case ID": "095835",
        "Different Crime": [
            {
                "Crime Name": "Working without authorization",
                "Crime Type": "Immigration-related_Fraud_or_Misrepresentation",
                "legal_basis": [
                    "IRPA section 48"
                ],
                "procedural_fairness": [
                    "reasonableness of Officer’s discretion",
                    "bias claims"
                ],
                "immigration_status": [
                    "working without authorization",
                    "removal orders"
                ],
                "decision_outcome": [
                    "Application dismissed"
                ],
                "misrepresentation_or_fraud": [
                    "failed to report income"
                ]
            },
            {
                "Crime Name": "Failure to report income to tax authorities",
                "Crime Type": "Economic_Crimes_or_Fraud-related_Offenses",
                "legal_basis": [
                    "Section 48 of IRPA"
                ],
                "decision_outcome": [
                    "removal orders as soon as practicable",
                    "no deferral granted"
                ],
                "procedural_fairness": [
                    "judicial review analyzed Officer's discretion under IRPA"
                ],
                "standard_of_review": [
                    "reasonableness"
                ],
                "nature_of_offense": [
                    "worked without authorization",
                    "failure to report income"
                ],
                "irreparable_harm": [
                    "no irreparable harm from removal"
                ],
                "appeal_outcome": [
                    "Application for judicial review dismissed"
                ]
            }
        ]
    },
    {
        "Case ID": "011486",
        "Different Crime": [
            {
                "Crime Name": "Overstaying visa",
                "Crime Type": "Immigration-related_Fraud_or_Misrepresentation",
                "best_interests_of_children": [
                    "children's short-term welfare",
                    "irreparable harm",
                    "Canadian-born children"
                ],
                "decision_outcome": [
                    "stay of removal"
                ],
                "legal_basis": [
                    "IRPA s. 48",
                    "Convention on the Rights of the Child"
                ],
                "family_class_considerations": [
                    "removal of a parent",
                    "Canadian-born children",
                    "precarious care"
                ],
                "procedural_fairness": [
                    "limited discretion",
                    "adequately consider"
                ],
                "humanitarian_and_compassionate_factors": [
                    "short-term child welfare",
                    "serious issue",
                    "balance of convenience"
                ]
            },
            {
                "Crime Name": "Failure to comply with reporting conditions",
                "Crime Type": "others",
                "best_interests_of_children": [
                    "best interests of children involved",
                    "children's best interests"
                ],
                "decision_reasoning": [
                    "removal officer did not adequately consider the children's best interests",
                    "constituting irreparable harm"
                ],
                "application_details": [
                    "applicant failed to comply with reporting conditions and resisted removal attempts"
                ],
                "relevant_statute": [
                    "IRPA s. 48"
                ],
                "procedure_followed": [
                    "Judicial review application and motion for stay of removal were filed"
                ],
                "result_of_case": [
                    "Removal was stayed pending full assessment of children's best interests or judicial review outcome"
                ],
                "cause_of_action": [
                    "Applicant's failure to comply with reporting conditions and removal attempts, coupled with concerns for her children's welfare"
                ]
            }
        ]
    },
    {
        "Case ID": "067744",
        "Different Crime": [
            {
                "Crime Name": "Use of fraudulent passport",
                "Crime Type": "Immigration-related_Fraud_or_Misrepresentation",
                "credibility_assessment": [
                    "inconsistent information about marital status, passport history, financial capability"
                ],
                "evidence_assessment": [
                    "use of fraudulent passport raised doubts about credibility"
                ],
                "refugee_status_eligibility": [
                    "claimed refugee status due to fear of forced sterilization in China"
                ],
                "decision_outcome": [
                    "application for judicial review dismissed; Board's decision upheld"
                ],
                "misrepresentation_or_fraud": [
                    "use of fraudulent passport"
                ]
            },
            {
                "Crime Name": "Failure to disclose material information",
                "Crime Type": "Economic_Crimes_or_Fraud-related_Offenses",
                "reasonableness_standard": [
                    "reasonableness"
                ],
                "credibility_assessment": [
                    "lack of credibility",
                    "inconsistent information"
                ],
                "evidence_provided": [
                    "inconsistent information",
                    "fraudulent documents"
                ],
                "judicial_authority": [
                    "Federal Court",
                    "Refugee Protection Division"
                ],
                "appeal_outcome": [
                    "dismissed"
                ],
                "risk_characterization": [
                    "risk of forced sterilization"
                ],
                "nexus_to_convention_grounds": [
                    "violating the one-child policy"
                ],
                "material_misrepresentation": [
                    "inconsistent information about marital status",
                    "use of fraudulent documents"
                ]
            }
        ]
    },
    {
        "Case ID": "098320",
        "Different Crime": [
            {
                "Crime Name": "Immigration Application Refusal",
                "Crime Type": "Economic_Crimes_or_Fraud-related_Offenses",
                "procedural_fairness": [
                    "meaningful notice of requests for additional information"
                ],
                "decision_outcome": [
                    "refusal of immigration applications"
                ],
                "evidence_provided": [
                    "non-receipt of emails",
                    "due diligence in maintaining email systems",
                    "DSN messages"
                ],
                "judicial_authority": [
                    "Judicial review application filed"
                ],
                "appeal_outcome": [
                    "Judicial review allowed",
                    "original decisions quashed",
                    "matters remitted for re-determination"
                ]
            }
        ]
    },
    {
        "Case ID": "077416",
        "Different Crime": [
            {
                "Crime Name": "Refugee Status Determination",
                "Crime Type": "Refugee_Claim-related_Issues",
                "credibility_findings": [
                    "veiled credibility finding",
                    "lack of clarity in credibility findings"
                ],
                "state_protection_analysis": [
                    "insufficient state protection analysis",
                    "consider personal circumstances"
                ],
                "decision_outcome": [
                    "case was remanded for re-determination"
                ],
                "legal_basis": [
                    "negative determination must include a clear credibility finding or treat allegations as true",
                    "judicial review application filed"
                ],
                "risk_of_persecution": [
                    "persecution by FARC"
                ]
            }
        ]
    },
    {
        "Case ID": "026274",
        "Different Crime": [
            {
                "Crime Name": "Immigration and Refugee Protection Act Violation",
                "Crime Type": "Human_Rights_or_International_Law_Violations",
                "legal_basis": [
                    "subsection 72(1) of the Immigration and Refugee Protection Act"
                ],
                "procedural_fairness": [
                    "officer's duty to assess all risks"
                ],
                "evidence_assessment": [
                    "insufficient evidence provided"
                ],
                "reasonableness_of_decision": [
                    "decision is unreasonable"
                ],
                "judicial_review_process": [
                    "judicial review application filed under IRPA subsection 72(1)"
                ],
                "decision_outcome": [
                    "application allowed",
                    "officer's decision set aside",
                    "PRRA application remitted for redetermination"
                ]
            }
        ]
    },
    {
        "Case ID": "024718",
        "Different Crime": [
            {
                "Crime Name": "Refugee Claim Dismissal",
                "Crime Type": "Refugee_Claim-related_Issues",
                "compelling_reasons_exception": [
                    "past persecution"
                ],
                "legal_basis": [
                    "s. 108(4) of the Act",
                    "s. 72(1) of the Immigration and Refugee Protection Act"
                ],
                "decision_outcome": [
                    "judicial review application allowed",
                    "case remitted for redetermination"
                ],
                "review_standard": [
                    "judicial review"
                ],
                "evidence_assessment": [
                    "psychological impacts on the Applicant"
                ],
                "burden_of_proof": [
                    "misapplication of 'compelling reasons'"
                ]
            }
        ]
    },
    {
        "Case ID": "016528",
        "Different Crime": [
            {
                "Crime Name": "Immigration and Refugee Protection Act Violation",
                "Crime Type": "Human_Rights_or_International_Law_Violations",
                "reasonableness_of_decision": [
                    "officer's failure to consider cumulative persecution"
                ],
                "procedural_fairness": [
                    "cumulative risk assessment under IRPA"
                ],
                "humanitarian_and_compassionate_grounds": [
                    "H&C decision contrasted with PRRA decision"
                ],
                "judicial_review_process": [
                    "judicial review application filed under IRPA subsection 72(1)"
                ],
                "decision_outcome": [
                    "judicial review allowed; PRRA and H&C decisions set aside for redetermination"
                ]
            }
        ]
    },
    {
        "Case ID": "062143",
        "Different Crime": [
            {
                "Crime Name": "Trademark Dispute",
                "Crime Type": "Economic_Crimes_or_Fraud-related_Offenses",
                "applicable_statute": [
                    "Trade-Marks Act"
                ],
                "evidence_provided": [
                    "use with ® symbol on shipping tape",
                    "affidavits and legal precedents"
                ],
                "decision_outcome": [
                    "appeal allowed",
                    "trademark reinstated",
                    "costs awarded to appellant"
                ],
                "cause_of_action": [
                    "expungement of trademark"
                ],
                "legal_basis": [
                    "Section 45 of the Trade-Marks Act"
                ],
                "use_in_trade": [
                    "Zircotex was used in Canada during the relevant period"
                ],
                "confusion_likelihood": [
                    "Additional words like 'Fix' or 'Alu' identified products, not source"
                ]
            }
        ]
    },
    {
        "Case ID": "041199",
        "Different Crime": [
            {
                "Crime Name": "False representation or fraud in obtaining citizenship",
                "Crime Type": "Immigration-related_Fraud_or_Misrepresentation",
                "legal_basis": [
                    "Section 18(1)(b) of the Citizenship Act",
                    "Section 29(2)(a) of the Citizenship Act"
                ],
                "misrepresentation_or_fraud": [
                    "knowingly concealing material circumstances",
                    "concealed criminal charges"
                ],
                "evidence_assessment": [
                    "respondent concealed criminal charges",
                    "aware of requirement to disclose information but failed to do so"
                ],
                "decision_outcome": [
                    "citizenship revocation warranted"
                ],
                "procedural_fairness": [
                    "Minister issued a notice of revocation",
                    "court proceedings with evidence and testimonies reviewed"
                ]
            }
        ]
    },
    {
        "Case ID": "016070",
        "Different Crime": [
            {
                "Crime Name": "unknown",
                "Crime Type": "others",
                "cause_of_action": [
                    "Dispute over leadership succession due to conflicting elections and customs."
                ],
                "procedural_fairness": [
                    "Judicial review of election processes, analysis of band customs, and consideration of administrative law principles."
                ],
                "administrative_decision": [
                    "Two groups claimed legitimacy as Chief and Council."
                ],
                "relevant_rule": [
                    "Administrative law principles, band custom, and electoral procedures govern the selection of leadership in Indigenous bands not subject to the Indian Act."
                ],
                "decision_reasoning": [
                    "Council No. 2 was elected without following proper procedures, including seeking a writ of quo warranto."
                ],
                "application_details": [
                    "A new Custom Leadership Selection Code was adopted by referendum, legitimizing Council No. 1's successor."
                ],
                "result_of_case": [
                    "Court dismissed the motion, confirming Council No. 1's legitimacy and upholding the new Custom Leadership Selection Code."
                ]
            }
        ]
    },
    {
        "Case ID": "003859",
        "Different Crime": [
            {
                "Crime Name": "unknown",
                "Crime Type": "others",
                "legal_basis": [
                    "subsection 41(1)(e) of the Canadian Human Rights Act"
                ],
                "decision_reasoning": [
                    "complaint was outside the one-year limit",
                    "no procedural unfairness occurred"
                ],
                "procedural_fairness": [
                    "Commission acted reasonably in not extending the time"
                ],
                "application_details": [
                    "Mr. Johnston argued his complaint was timely or should have had the time limit extended"
                ],
                "cause_of_action": [
                    "gender discrimination at work"
                ],
                "procedure_followed": [
                    "Judicial review assessed whether the Commission erred in dismissing the complaint based on timeliness and procedural fairness"
                ],
                "result_of_case": [
                    "The court dismissed the application, upholding the Commission's decision"
                ]
            }
        ]
    },
    {
        "Case ID": "026376",
        "Different Crime": [
            {
                "Crime Name": "Refugee Claim Dismissal",
                "Crime Type": "Refugee_Claim-related_Issues",
                "credibility_findings": [
                    "delayed departure",
                    "returns to Haiti",
                    "no asylum claim in the U.S.",
                    "evasive testimony"
                ],
                "reasonableness_standard": [
                    "mixed questions of fact and law"
                ],
                "risk_of_persecution": [
                    "alleged persecution by an armed gang in Haiti"
                ],
                "evidence_assessment": [
                    "tribunal's findings regarding credibility, evidence treatment"
                ],
                "decision_outcome": [
                    "dismissed the judicial review application"
                ],
                "standard_of_review": [
                    "reasonableness"
                ]
            }
        ]
    },
    {
        "Case ID": "094400",
        "Different Crime": [
            {
                "Crime Name": "Refugee Claim Rejection",
                "Crime Type": "Refugee_Claim-related_Issues",
                "legal_basis": [
                    "IRPA ss. 96 and 97"
                ],
                "credibility_findings": [
                    "lack of credible evidence"
                ],
                "gender_guidelines": [
                    "gender-based analysis",
                    "gender-specific risks"
                ],
                "documentary_evidence": [
                    "targeted violence against women"
                ],
                "decision_outcome": [
                    "claim dismissed"
                ],
                "risk_of_persecution": [
                    "generalized violence",
                    "political persecution",
                    "gender-based fear"
                ],
                "evidence_assessment": [
                    "insufficient evidence of political involvement"
                ],
                "review_standard": [
                    "judicial review"
                ],
                "specific_group_membership": [
                    "particular social group",
                    "women"
                ],
                "nexus_to_convention_grounds": [
                    "political opinion",
                    "membership in a particular social group"
                ],
                "independent_review_by_rad": [
                    "new hearing with a differently constituted Board"
                ],
                "standard_of_proof": [
                    "Board erred in law"
                ],
                "burden_of_proof": [
                    "insufficient evidence"
                ],
                "contextual_factors": [
                    "targeted violence against women"
                ]
            }
        ]
    },
    {
        "Case ID": "059832",
        "Different Crime": [
            {
                "Crime Name": "Unlawful assault",
                "Crime Type": "Violence-related_Crimes",
                "procedural_fairness": [
                    "duty to act fairly",
                    "calling additional witnesses"
                ],
                "evidence_consideration": [
                    "rules of evidence",
                    "conflicting stories",
                    "reviewed evidence for fairness"
                ],
                "risk_assessment": [
                    "self-defense justification",
                    "mild push",
                    "threatening response"
                ],
                "serious_issue": [
                    "misinterpretation of law",
                    "breach of fairness"
                ]
            }
        ]
    },
    {
        "Case ID": "097512",
        "Different Crime": [
            {
                "Crime Name": "unknown",
                "Crime Type": "others",
                "legal_basis": [
                    "Citizenship Act"
                ],
                "procedural_fairness": [
                    "no breach of procedural fairness"
                ],
                "decision_reasoning": [
                    "Ms. Huang failed to meet residency requirements"
                ],
                "application_details": [
                    "Ms. Huang argued that her rights were breached due to insufficient notice and improper assessment of her residence and English proficiency"
                ],
                "standard_of_review": [
                    "correctness for procedural fairness",
                    "reasonableness for mixed fact and law issues"
                ],
                "conclusion_outcome": [
                    "The appeal was dismissed"
                ],
                "result_of_case": [
                    "The court upheld the citizenship judge's decision, dismissing Ms. Huang's appeal"
                ]
            }
        ]
    },
    {
        "Case ID": "002393",
        "Different Crime": [
            {
                "Crime Name": "Citizenship Residency Requirement Violation",
                "Crime Type": "Immigration-related_Fraud_or_Misrepresentation",
                "residency_requirements": [
                    "1,095 days over four years"
                ],
                "standard_of_review": [
                    "reasonableness"
                ],
                "evidence_assessment": [
                    "discrepancies in applicant's evidence",
                    "missing re-entry stamps",
                    "incomplete documentation"
                ],
                "credibility_assessment": [
                    "travel history as credible despite gaps"
                ],
                "decision_outcome": [
                    "citizenship judge's decision reasonable",
                    "application for judicial review dismissed"
                ]
            }
        ]
    },
    {
        "Case ID": "091704",
        "Different Crime": [
            {
                "Crime Name": "unknown",
                "Crime Type": "others",
                "patent_validity": [
                    "'203 Patent is valid for Claims 5, 7, 29, 44, and 46",
                    "Claims 1-4 are invalid"
                ],
                "relevant_statute": [
                    "Patent Act"
                ],
                "evidence_presented": [
                    "expert testimonies",
                    "analysis of patent specifications",
                    "evaluation of testing data"
                ],
                "infringement_analysis": [
                    "Apotex's remaining bulk imatinib was exempt from infringement under regulatory use exemptions"
                ],
                "decision_reasoning": [
                    "sound prediction was supported by prior art and disclosed data",
                    "fulfilling utility requirements",
                    "Disclosure included methods and results sufficient for skilled persons to practice the invention"
                ],
                "application_details": [
                    "Teva and Apotex sought to invalidate Novartis's '203 Patent claiming selective kinase inhibitors"
                ],
                "conclusion_outcome": [
                    "Most claims of the '203 Patent were upheld as valid"
                ],
                "specific_rule_applied": [
                    "a patent must describe an invention that is both new and useful",
                    "Utility can be demonstrated or soundly predicted based on factual basis, articulable reasoning, and adequate disclosure in the patent"
                ]
            }
        ]
    },
    {
        "Case ID": "018902",
        "Different Crime": [
            {
                "Crime Name": "unknown",
                "Crime Type": "others",
                "credibility_findings": [
                    "implausible actions",
                    "inconsistencies in PSB visits",
                    "lack of objective evidence",
                    "insufficient proof of church membership"
                ],
                "standard_of_review": [
                    "reasonableness standard"
                ],
                "decision_reasoning": [
                    "Board's credibility findings were reasonable and supported by evidence"
                ],
                "application_details": [
                    "applicant's claim of religious persecution"
                ],
                "procedure_followed": [
                    "Judicial review in Federal Court"
                ],
                "result_of_case": [
                    "application for judicial review was dismissed"
                ]
            }
        ]
    },
    {
        "Case ID": "024481",
        "Different Crime": [
            {
                "Crime Name": "Trademark Dispute",
                "Crime Type": "Economic_Crimes_or_Fraud-related_Offenses",
                "legal_basis": [
                    "Section 6 of the Trade-marks Act"
                ],
                "confusion_analysis": [
                    "distinctiveness",
                    "length of use",
                    "nature of wares/services",
                    "trade nature",
                    "resemblance in appearance, sound, or suggested ideas"
                ],
                "standard_of_review": [
                    "reasonableness standard"
                ],
                "appeal_outcome": [
                    "dismissed"
                ],
                "decision_outcome": [
                    "upheld the Registrar's decision"
                ],
                "confusion_likelihood": [
                    "phonetic resemblance",
                    "shared term 'Monte Carlo'",
                    "overlapping services",
                    "potential future market overlap"
                ]
            }
        ]
    },
    {
        "Case ID": "094229",
        "Different Crime": [
            {
                "Crime Name": "Refugee Status Claim",
                "Crime Type": "Refugee_Claim-related_Issues",
                "reasonableness_standard": [
                    "standard of review for credibility and objective fear"
                ],
                "documentary_evidence": [
                    "Colombia's situation improved since the alleged persecution"
                ],
                "credibility_findings": [
                    "applicant delayed actions consistent with fear"
                ],
                "risk_of_persecution": [
                    "fear of FARC, citing threats against his family"
                ],
                "decision_outcome": [
                    "SPR's decision reasonable, judicial review application dismissed"
                ],
                "evidence_assessment": [
                    "lack of credible fear"
                ],
                "country_conditions": [
                    "Colombia's situation improved"
                ]
            }
        ]
    },
    {
        "Case ID": "026562",
        "Different Crime": [
            {
                "Crime Name": "Misrepresentation under Immigration and Refugee Protection Act",
                "Crime Type": "Immigration-related_Fraud_or_Misrepresentation",
                "legal_basis": [
                    "Immigration and Refugee Protection Act",
                    "section 248 of the Regulations"
                ],
                "procedural_fairness": [
                    "Judicial review by Federal Court"
                ],
                "misrepresentation_or_fraud": [
                    "Applicant's history shows non-compliance with CBSA procedures"
                ],
                "decision_outcome": [
                    "Application dismissed; continued detention upheld as reasonable"
                ],
                "standard_of_review": [
                    "Decisions are reviewed for reasonableness"
                ]
            },
            {
                "Crime Name": "Immigration Fraud",
                "Crime Type": "Economic_Crimes_or_Fraud-related_Offenses",
                "balance_of_convenience": [
                    "liberty interests vs public interest"
                ],
                "flight_risk": [
                    "high risk due to history of non-compliance"
                ],
                "reasonableness_standard": [
                    "Board's decision reviewed for reasonableness"
                ],
                "past_behavior": [
                    "history of lying to authorities, missing interviews"
                ],
                "relationship_genuineness": [
                    "doubts about bondsmen's influence"
                ],
                "judicial_authority": [
                    "Federal Court"
                ],
                "appeal_outcome": [
                    "dismissed"
                ],
                "decision_outcome": [
                    "continue detention until next review"
                ]
            }
        ]
    },
    {
        "Case ID": "045959",
        "Different Crime": [
            {
                "Crime Name": "Immigration Visa Denial",
                "Crime Type": "others",
                "procedural_fairness": [
                    "procedurally fair"
                ],
                "discretion_exercise": [
                    "visa officers have discretion to refuse applications"
                ],
                "evidence_assessment": [
                    "applicant lacked experience",
                    "financial instability",
                    "questionable intentions to return"
                ],
                "decision_reasoning": [
                    "substantively reasonable"
                ],
                "result_of_case": [
                    "Application for judicial review dismissed"
                ]
            }
        ]
    },
    {
        "Case ID": "079773",
        "Different Crime": [
            {
                "Crime Name": "Immigration and Refugee Protection Act Violation",
                "Crime Type": "Human_Rights_or_International_Law_Violations",
                "procedural_fairness": [
                    "considered all relevant evidence",
                    "applied the correct legal test"
                ],
                "humanitarian_and_compassionate_grounds": [
                    "best interests of children"
                ],
                "reasonableness_of_decision": [
                    "decision reasonable and procedurally fair"
                ],
                "judicial_review_process": [
                    "judicial review of the immigration officer's decision in Federal Court"
                ],
                "burden_of_proof": [
                    "officers must consider humanitarian and compassionate grounds, including the best interests of children"
                ]
            }
        ]
    },
    {
        "Case ID": "090043",
        "Different Crime": [
            {
                "Crime Name": "Pre-Removal Risk Assessment (PRRA) Appeal",
                "Crime Type": "Economic_Crimes_or_Fraud-related_Offenses",
                "standard_of_review": [
                    "reasonableness"
                ],
                "risk_characterization": [
                    "personalized risk"
                ],
                "evidence_provided": [
                    "no new evidence of risk"
                ],
                "decision_outcome": [
                    "dismissed"
                ],
                "procedural_fairness": [
                    "justification, transparency, and intelligibility"
                ],
                "judicial_authority": [
                    "Court upheld the PRRA decision"
                ]
            }
        ]
    },
    {
        "Case ID": "099397",
        "Different Crime": [
            {
                "Crime Name": "Discrimination based on race and color",
                "Crime Type": "Human_Rights_or_International_Law_Violations",
                "legal_basis": [
                    "Canadian Human Rights Act"
                ],
                "procedural_fairness": [
                    "breach of duty of fairness",
                    "insufficient investigation"
                ],
                "evidentiary_standard": [
                    "focus on intent and motivation rather than circumstantial evidence"
                ],
                "specific_legal_test_application": [
                    "incorrect legal standards applied"
                ],
                "judicial_review_process": [
                    "judicial review of the Commission's decision"
                ],
                "decision_outcome": [
                    "set aside",
                    "referred back for reinvestigation"
                ]
            }
        ]
    },
    {
        "Case ID": "054431",
        "Different Crime": [
            {
                "Crime Name": "unknown",
                "Crime Type": "others",
                "standard_of_review": [
                    "reasonableness"
                ],
                "procedural_fairness": [
                    "disclosing extrinsic evidence unless publicly available"
                ],
                "evidence_assessment": [
                    "consider all evidence but not required to explicitly label every factor"
                ],
                "humanitarian_and_compassionate_considerations": [
                    "establishment, emotional hardship, impact on employer"
                ],
                "decision_reasoning": [
                    "emotional hardship implicitly assessed, establishment balanced against family ties"
                ],
                "result_of_case": [
                    "Federal Court dismissed the application, upholding the officer's decision"
                ]
            }
        ]
    },
    {
        "Case ID": "025812",
        "Different Crime": [
            {
                "Crime Name": "Fraudulent Means or Misrepresentation in Immigration Context",
                "Crime Type": "Immigration-related_Fraud_or_Misrepresentation",
                "standard_of_review": [
                    "correctness"
                ],
                "procedural_fairness": [
                    "natural justice",
                    "reasonableness standard"
                ],
                "evidence_assessment": [
                    "insufficient evidence of risk",
                    "lack of state protection attempts"
                ],
                "misrepresentation_or_fraud": [
                    "consultant's incompetence",
                    "failure to file written submissions"
                ],
                "decision_outcome": [
                    "application for judicial review dismissed",
                    "PRRA application denied"
                ]
            },
            {
                "Crime Name": "False Documents",
                "Crime Type": "Economic_Crimes_or_Fraud-related_Offenses",
                "procedural_fairness": [
                    "natural justice",
                    "fairness"
                ],
                "standard_of_review": [
                    "correctness"
                ],
                "reasonableness_standard": [
                    "reasonableness standard",
                    "reasonable professional assistance"
                ],
                "evidence_provided": [
                    "lacked objective evidence",
                    "new evidence post-decision"
                ],
                "judicial_authority": [
                    "court dismissed the application"
                ],
                "appeal_outcome": [
                    "rejected"
                ],
                "cause_of_action": [
                    "PRRA application denied",
                    "consultant incompetence"
                ],
                "relationship_genuineness": [
                    "failed to file written submissions"
                ],
                "state_protection": [
                    "attempts of state protection"
                ]
            },
            {
                "Crime Name": "False Documents",
                "Crime Type": "Terrorism_or_National_Security-related_Crimes",
                "procedural_fairness": [
                    "natural justice",
                    "fairness"
                ],
                "reasonableness_standard": [
                    "reasonableness standard",
                    "reasonable professional assistance"
                ],
                "evidence_provided": [
                    "written submissions",
                    "objective evidence of state protection attempts",
                    "new evidence post-decision"
                ],
                "judicial_review_result": [
                    "application dismissed",
                    "insufficient evidence of incompetence or prejudice"
                ],
                "decision_outcome": [
                    "PRRA application denied"
                ],
                "standard_of_proof": [
                    "correctness",
                    "competence must be proven"
                ]
            },
            {
                "Crime Name": "Unknown",
                "Crime Type": "others",
                "legal_basis": [
                    "natural justice",
                    "procedural fairness"
                ],
                "standard_of_review": [
                    "correctness"
                ],
                "decision_reasoning": [
                    "insufficient evidence of incompetence or prejudice"
                ],
                "application_details": [
                    "PRRA application",
                    "consultant's actions"
                ],
                "result_of_case": [
                    "judicial review dismissed"
                ],
                "evidence_assessment": [
                    "no objective evidence of incompetence"
                ]
            }
        ]
    },
    {
        "Case ID": "090613",
        "Different Crime": [
            {
                "Crime Name": "Misrepresentation in immigration process",
                "Crime Type": "Immigration-related_Fraud_or_Misrepresentation",
                "humanitarian_and_compassionate_factors": [
                    "insufficient H&C grounds"
                ],
                "best_interests_of_children": [
                    "considered under Section 25"
                ],
                "misrepresentation_or_fraud": [
                    "parents misrepresented children's existence"
                ],
                "family_class_considerations": [
                    "excluded children from sponsorship"
                ],
                "standard_of_review": [
                    "correct standard applied"
                ],
                "decision_outcome": [
                    "upheld officer's decision"
                ]
            }
        ]
    },
    {
        "Case ID": "030171",
        "Different Crime": [
            {
                "Crime Name": "Patent Law Dispute",
                "Crime Type": "Economic_Crimes_or_Fraud-related_Offenses",
                "legal_basis": [
                    "Canadian law"
                ],
                "patent_validity": [
                    "determined solely by its issued terms"
                ],
                "procedural_fairness": [
                    "representations made during patent prosecution cannot alter the patent's scope or create estoppel"
                ],
                "appeal_outcome": [
                    "allowed the appeal, striking out the paragraphs"
                ],
                "decision_outcome": [
                    "Paragraphs relying on patent prosecution history for estoppel were struck out"
                ],
                "cause_of_action": [
                    "Plaintiffs sought to strike out paragraphs in defendants' defense alleging estoppel based on patent prosecution statements"
                ]
            }
        ]
    },
    {
        "Case ID": "053540",
        "Different Crime": [
            {
                "Crime Name": "Patent Infringement Dispute",
                "Crime Type": "Economic_Crimes_or_Fraud-related_Offenses",
                "patent_validity": [
                    "plaintiffs won on the issue of patent validity"
                ],
                "expert_testimony": [
                    "expert witness fees"
                ],
                "decision_outcome": [
                    "Plaintiffs received costs award subject to assessment, with specific offsets for defendant's costs"
                ],
                "legal_basis": [
                    "Successful parties in litigation are generally entitled to costs"
                ],
                "procedural_fairness": [
                    "balance compensation for the winner and not overly burden the loser"
                ],
                "cause_of_action": [
                    "Dispute over patent validity and infringement leading to a trial where plaintiffs prevailed"
                ]
            }
        ]
    },
    {
        "Case ID": "027284",
        "Different Crime": [
            {
                "Crime Name": "Immigration Application Dismissal",
                "Crime Type": "Immigration-related_Fraud_or_Misrepresentation",
                "humanitarian_and_compassionate_factors": [
                    "hardship due to integration into Canada and risks in Guinea"
                ],
                "procedural_fairness": [
                    "no unusual or disproportionate hardship found",
                    "all evidence considered",
                    "no requirement for interview"
                ],
                "legal_basis": [
                    "Immigration and Refugee Protection Act, s. 25"
                ],
                "decision_outcome": [
                    "application for judicial review dismissed"
                ],
                "standard_of_review": [
                    "reasonableness"
                ]
            }
        ]
    },
    {
        "Case ID": "095993",
        "Different Crime": [
            {
                "Crime Name": "Refugee Claim Dismissal",
                "Crime Type": "Refugee_Claim-related_Issues",
                "legal_basis": [
                    "Canadian law, refugee claimants must demonstrate that state protection is unavailable"
                ],
                "state_protection_analysis": [
                    "presumption of state protection in democratic nations unless rebutted by clear evidence"
                ],
                "reasonableness_standard": [
                    "Federal Court reviewed the Board's decision under reasonableness standard"
                ],
                "risk_of_persecution": [
                    "Applicants claimed persecution by FARC"
                ],
                "decision_outcome": [
                    "Application for judicial review dismissed; no certification question granted"
                ],
                "procedural_fairness": [
                    "applicant's additional affidavit was struck due to procedural issues"
                ]
            }
        ]
    },
    {
        "Case ID": "099731",
        "Different Crime": [
            {
                "Crime Name": "unknown",
                "Crime Type": "others",
                "legal_basis": [
                    "Immigration and Refugee Protection Act"
                ],
                "standard_of_review": [
                    "reasonableness"
                ],
                "state_protection": [
                    "adequate state protection",
                    "presumption of state protection",
                    "rebutted by clear and convincing evidence"
                ],
                "decision_reasoning": [
                    "Board's decision was reasonable",
                    "within acceptable outcomes"
                ],
                "cause_of_action": [
                    "fear of persecution",
                    "blood feud in Albania"
                ],
                "result_of_case": [
                    "application for judicial review dismissed",
                    "no certified questions under section 74"
                ]
            }
        ]
    },
    {
        "Case ID": "076163",
        "Different Crime": [
            {
                "Crime Name": "Kidnapping",
                "Crime Type": "Violence-related_Crimes",
                "legal_basis": [
                    "Corrections and Conditional Release Act (CCRA)",
                    "Section 223",
                    "Section 102"
                ],
                "procedural_fairness": [
                    "retroactive application",
                    "continuity of process",
                    "Charter rights"
                ],
                "risk_assessment": [
                    "moderate-high risk"
                ],
                "past_criminal_convictions": [
                    "indeterminate sentence for kidnapping and other offenses"
                ],
                "rehabilitation_or_possibility": [
                    "recent gains"
                ],
                "standard_of_proof": [
                    "reasonableness of decision"
                ]
            }
        ]
    },
    {
        "Case ID": "000109",
        "Different Crime": [
            {
                "Crime Name": "Immigration Violation",
                "Crime Type": "Violence-related_Crimes",
                "legal_basis": [
                    "subsection 72(1) of the Immigration and Refugee Protection Act"
                ],
                "procedural_fairness": [
                    "patent unreasonableness"
                ],
                "evidence_consideration": [
                    "insufficient documentation",
                    "likelihood of departure",
                    "ties to Pakistan",
                    "lack of financial proof",
                    "international travel history"
                ],
                "availability_of_alternative_remedies": [
                    "judicial review"
                ],
                "reasonableness_of_decision": [
                    "patently unreasonable"
                ],
                "immigration_status": [
                    "temporary resident visa"
                ],
                "applicant_characteristics": [
                    "weak ties to home country"
                ]
            },
            {
                "Crime Name": "Immigration Violation",
                "Crime Type": "Weapons_or_Explosives-related_Crimes",
                "legal_basis": [
                    "subsection 72(1) of the Immigration and Refugee Protection Act"
                ],
                "procedural_fairness": [
                    "patent unreasonableness"
                ],
                "evidence_considered": [
                    "ties to Pakistan",
                    "financial proof",
                    "international travel history"
                ],
                "decision_outcome": [
                    "judicial review granted",
                    "decision quashed",
                    "re-determination by another officer"
                ],
                "standard_of_review": [
                    "patent unreasonableness"
                ]
            }
        ]
    }
]