[
    {
        "Case ID": "057004",
        "Different Crime": [
            {
                "Crime Name": "unknown",
                "Crime Type": "others",
                "legal_basis": [
                    "sections 18(b) and 20(1)(b), (c), and (d) of the Access to Information Act"
                ],
                "evidence_assessment": [
                    "confidential scientific data",
                    "could harm C.E.R.L.'s competitive position"
                ],
                "decision_reasoning": [
                    "properly exercised discretion under section 18(b)",
                    "upheld under sections 20(1)(c) and (d)"
                ],
                "application_details": [
                    "Lindsey Hutton sought access to records related to studies conducted by C.E.R.L."
                ],
                "procedure_followed": [
                    "filed a complaint with the Information Commissioner",
                    "applied for judicial review under section 41 of the Act"
                ],
                "result_of_case": [
                    "court dismissed the application",
                    "upholding the Minister’s decision to deny access"
                ]
            }
        ]
    },
    {
        "Case ID": "092365",
        "Different Crime": [
            {
                "Crime Name": "unknown",
                "Crime Type": "others",
                "legal_basis": [
                    "Access to Information Act",
                    "sections 20(1)(b)",
                    "20(1)(c)",
                    "Section 25"
                ],
                "procedural_fairness": [
                    "de novo review"
                ],
                "evidence_assessment": [
                    "record analysis",
                    "confidentiality criteria",
                    "potential harm assessment"
                ],
                "decision_reasoning": [
                    "exemption criteria met for some records",
                    "severance of non-exempt portions"
                ],
                "applicable_regulations": [
                    "Access to Information Act"
                ],
                "discretion_exercise": [
                    "partial disclosure",
                    "withholding based on confidentiality or potential harm"
                ],
                "application_details": [
                    "third-party information",
                    "City Express operational records"
                ],
                "conclusion_outcome": [
                    "partial disclosure ordered",
                    "some records withheld entirely"
                ],
                "cause_of_action": [
                    "request for access under Access to Information Act"
                ],
                "procedure_followed": [
                    "Federal Court review",
                    "statutory exemptions examination"
                ],
                "result_of_case": [
                    "partial disclosure",
                    "severance where applicable",
                    "costs awarded to City Express"
                ],
                "specific_rule_applied": [
                    "sections 20(1)(b)",
                    "20(1)(c)",
                    "Section 25"
                ],
                "party_involved": [
                    "City Express",
                    "Minister of Transport"
                ],
                "decision_made": [
                    "partial disclosure",
                    "severance of exempt portions"
                ],
                "relevant_statute": [
                    "Access to Information Act"
                ],
                "claim_nature": [
                    "confidentiality and potential harm dispute"
                ],
                "court_jurisdiction": [
                    "Federal Court"
                ],
                "application_context": [
                    "third-party information confidentiality"
                ],
                "procedure_steps": [
                    "record analysis",
                    "exemption criteria evaluation"
                ],
                "result_details": [
                    "partial disclosure",
                    "severance of non-exempt portions",
                    "costs awarded"
                ],
                "relevant_rule": [
                    "sections 20(1)(b)",
                    "20(1)(c)",
                    "Section 25"
                ],
                "decision_standard": [
                    "de novo review"
                ],
                "evidence_type": [
                    "operational records"
                ],
                "dispute_focus": [
                    "confidentiality vs. disclosure"
                ],
                "court_ruling": [
                    "partial disclosure",
                    "severance where applicable"
                ],
                "remedy_requested": [
                    "protection of confidential information"
                ],
                "standard_of_proof": [
                    "exemption criteria satisfaction"
                ],
                "reasonableness_of_decision": [
                    "evaluation of each record against statutory exemptions"
                ],
                "discretionary_factors": [
                    "confidentiality",
                    "potential harm",
                    "severability"
                ],
                "jurisdictional_issues": [
                    "Federal Court jurisdiction over Access to Information Act matters"
                ],
                "administrative_decision": [
                    "Minister of Transport's decision to release records"
                ],
                "cause_incident": [
                    "third-party request for operational records"
                ],
                "rule_regulation": [
                    "Access to Information Act exemptions"
                ],
                "breach_of_fairness": [
                    "none identified"
                ],
                "humanitarian_and_compassionate_considerations": [],
                "refugee_status": [],
                "mitigating_factors": [],
                "aggravating_factors": [],
                "witness_testimony": [],
                "precedent_cited": [],
                "application_submitted": [
                    "challenge to Minister of Transport's decision"
                ],
                "rule_applied": [
                    "sections 20(1)(b)",
                    "20(1)(c)",
                    "Section 25"
                ],
                "parties_involved": [
                    "City Express",
                    "Minister of Transport"
                ],
                "residency_requirement": [],
                "risk_assessment": [
                    "confidentiality and potential harm"
                ],
                "forfeiture_proportionality": [],
                "evidence_consideration": [
                    "record-by-record analysis"
                ],
                "decision_reasonableness": [
                    "application of statutory exemptions"
                ],
                "immigration_status": [],
                "cumulative_effects": [],
                "constitutional_rights": [],
                "evidentiary_standard": [
                    "exemption criteria satisfaction"
                ],
                "child_best_interests": [],
                "financial_impact": [],
                "best_interests_of_children": [],
                "personalized_vs_generalized_risk": [],
                "substantive_consultation": [],
                "charter_rights_impact": [],
                "de_novo_hearing": [
                    "yes"
                ],
                "appeal_outcome": [
                    "partial disclosure, severance where applicable"
                ],
                "refugee_criteria": [],
                "immigration_policy": [],
                "bond_forfeiture": [],
                "contract_interpretation": []
            }
        ]
    },
    {
        "Case ID": "002632",
        "Different Crime": [
            {
                "Crime Name": "unknown",
                "Crime Type": "others",
                "legal_basis": [
                    "Sections 19(1)",
                    "20(1) of the Access to Information Act"
                ],
                "evidence_assessment": [
                    "financial statements contain private financial information of Indian Bands"
                ],
                "decision_reasoning": [
                    "confidential third-party information",
                    "fiduciary relationship"
                ],
                "conclusion_outcome": [
                    "exempt from disclosure under s. 20(1)(b)"
                ],
                "result_of_case": [
                    "application allowed with costs"
                ]
            }
        ]
    },
    {
        "Case ID": "058909",
        "Different Crime": [
            {
                "Crime Name": "unknown",
                "Crime Type": "others",
                "legal_basis": [
                    "Access to Information Act",
                    "Sections 19, 23, and 25"
                ],
                "cause_of_action": [
                    "denied access citing exemptions under the Access to Information Act"
                ],
                "procedure_followed": [
                    "Judicial review initiated after complaints to the Information Commissioner. Court reviewed documents and legal arguments"
                ],
                "decision_reasoning": [
                    "Main Record: The Senior Public Rights Administrator incorrectly applied Section 19(2). Secret Record: Most pages were exempt under Sections 19 and 23 due to personal information or solicitor-client privilege"
                ],
                "result_of_case": [
                    "Court ordered reevaluation of Main Record and upheld nondisclosure of most Secret Record pages while dismissing claims on irrelevant pages."
                ],
                "conclusion_outcome": [
                    "Main Record must be redetermined by a different official. Secret Record's nondisclosure upheld for privileged/personal information pages"
                ]
            }
        ]
    },
    {
        "Case ID": "061298",
        "Different Crime": [
            {
                "Crime Name": "unknown",
                "Crime Type": "others",
                "legal_basis": [
                    "Section 23 of the Access to Information Act"
                ],
                "procedural_fairness": [
                    "waiver analysis",
                    "discretion exercise"
                ],
                "evidence_assessment": [
                    "precedent analysis",
                    "statutory interpretation"
                ],
                "decision_reasoning": [
                    "solicitor-client privilege applicability",
                    "no waiver found"
                ],
                "result_of_case": [
                    "application dismissed"
                ]
            }
        ]
    },
    {
        "Case ID": "067976",
        "Different Crime": [
            {
                "Crime Name": "unknown",
                "Crime Type": "others",
                "legal_basis": [
                    "Privacy Act",
                    "Sections 24, 25, and 26 of the Privacy Act",
                    "s. 41 of the Privacy Act"
                ],
                "procedural_fairness": [
                    "judicial review"
                ],
                "evidence_assessment": [
                    "factual and discretionary decisions"
                ],
                "decision_reasoning": [
                    "discretionary exemptions justified except for two pages"
                ],
                "applicable_regulations": [
                    "Privacy Act"
                ],
                "specific_rule_applied": [
                    "Sections 24, 25, and 26 of the Privacy Act"
                ],
                "result_of_case": [
                    "application dismissed except for release of two specific pages"
                ],
                "decision_made": [
                    "Correctional Service properly exercised its discretion"
                ],
                "relevant_statute": [
                    "Privacy Act"
                ],
                "court_ruling": [
                    "most information remains withheld, two pages must be disclosed"
                ],
                "procedure_followed": [
                    "judicial review under s. 41 of the Privacy Act"
                ],
                "cause_of_action": [
                    "request for personal information leading to disputes over exemptions"
                ]
            }
        ]
    },
    {
        "Case ID": "035550",
        "Different Crime": [
            {
                "Crime Name": "Immigration and Refugee Status",
                "Crime Type": "Refugee_Claim-related_Issues",
                "review_standard": [
                    "bad faith",
                    "irrelevant considerations",
                    "patently unreasonable actions"
                ],
                "country_conditions": [
                    "changes in country conditions"
                ],
                "documentary_evidence": [
                    "objective documentary evidence"
                ],
                "specific_threats": [
                    "no conclusive evidence of specific threats"
                ],
                "procedural_fairness": [
                    "extrinsic evidence was used without applicant knowledge"
                ],
                "decision_outcome": [
                    "application for judicial review dismissed"
                ],
                "risk_of_persecution": [
                    "risk due to past events in Guatemala"
                ]
            }
        ]
    },
    {
        "Case ID": "015072",
        "Different Crime": [
            {
                "Crime Name": "Immigration Application Dismissal",
                "Crime Type": "Immigration-related_Fraud_or_Misrepresentation",
                "procedural_fairness": [
                    "breach of procedural fairness",
                    "duty of fairness"
                ],
                "evidence_assessment": [
                    "inadequate documentation",
                    "submitted documents"
                ],
                "decision_outcome": [
                    "application dismissed",
                    "judicial review dismissed"
                ],
                "standard_of_review": [
                    "reasonableness",
                    "Immigration and Refugee Protection Act"
                ],
                "immigration_status": [
                    "visa application",
                    "family relationships"
                ]
            }
        ]
    },
    {
        "Case ID": "035083",
        "Different Crime": [
            {
                "Crime Name": "Refugee Claim Dismissal",
                "Crime Type": "Refugee_Claim-related_Issues",
                "credibility_findings": [
                    "missing documentation",
                    "inconsistencies"
                ],
                "procedural_fairness": [
                    "no breach found"
                ],
                "reasonableness_standard": [
                    "applies to credibility assessments"
                ],
                "documentary_evidence": [
                    "lack of key documents"
                ],
                "evidence_assessment": [
                    "RPD considered omissions reasonable grounds for doubting credibility"
                ],
                "decision_outcome": [
                    "application dismissed"
                ],
                "burden_of_proof": [
                    "not explicitly breached"
                ],
                "review_standard": [
                    "correctness for procedural fairness",
                    "reasonableness for credibility"
                ]
            }
        ]
    },
    {
        "Case ID": "013428",
        "Different Crime": [
            {
                "Crime Name": "unknown",
                "Crime Type": "others",
                "standard_of_review": [
                    "reasonableness"
                ],
                "decision_reasonableness": [
                    "failure to assess state protection adequacy"
                ],
                "state_protection": [
                    "Hungary's state protection measures"
                ],
                "risk_of_persecution": [
                    "racial violence"
                ],
                "application_details": [
                    "asylum claim in Canada"
                ],
                "result_of_case": [
                    "judicial review granted",
                    "case remanded to a new panel"
                ]
            }
        ]
    },
    {
        "Case ID": "035671",
        "Different Crime": [
            {
                "Crime Name": "Crimes against humanity",
                "Crime Type": "Human_Rights_or_International_Law_Violations",
                "legal_basis": [
                    "paragraph 1F(a) of the Geneva Convention",
                    "subsection 72(1) of the Immigration and Refugee Protection Act"
                ],
                "credibility_findings": [
                    "vague testimony",
                    "lacking credibility"
                ],
                "evidence_assessment": [
                    "documentary evidence showing contribution to crimes"
                ],
                "decision_outcome": [
                    "application dismissed",
                    "Board's decision upheld"
                ],
                "refugee_definition": [
                    "exclusion under paragraph 1F(a)"
                ],
                "complicity_in_crimes": [
                    "voluntary collaboration with army committing crimes against humanity"
                ],
                "reasonableness_of_decision": [
                    "reasonable based on evidence and applicable law"
                ],
                "judicial_review_process": [
                    "assessing reasonableness of Board’s decision"
                ]
            }
        ]
    },
    {
        "Case ID": "079759",
        "Different Crime": [
            {
                "Crime Name": "unknown",
                "Crime Type": "others",
                "court_jurisdiction": [
                    "Federal Court",
                    "BC Supreme Court"
                ],
                "relevant_statute": [
                    "Federal Court Act (Sections 17, 18, 25, 44)"
                ],
                "cause_of_action": [
                    "Dispute over election validity"
                ],
                "procedure_followed": [
                    "Initial proceedings dismissed in BC Supreme Court",
                    "Subsequent actions filed in Federal Court"
                ],
                "decision_reasoning": [
                    "No statutory grant of jurisdiction under Sections 17 or 18",
                    "Sections 25 and 44 do not provide jurisdiction",
                    "Improper framing as application rather than judicial review"
                ],
                "conclusion_outcome": [
                    "Federal Court lacks jurisdiction",
                    "Election would have been upheld on merits"
                ],
                "result_of_case": [
                    "Main action and counterclaim dismissed"
                ]
            }
        ]
    },
    {
        "Case ID": "042328",
        "Different Crime": [
            {
                "Crime Name": "Trafficking in a controlled substance",
                "Crime Type": "Drug-related_Crimes",
                "legal_basis": [
                    "IRPA s. 64(2)"
                ],
                "serious_criminality": [
                    "punished by imprisonment of at least two years"
                ],
                "decision_outcome": [
                    "appeal to the IAD was barred",
                    "application for judicial review dismissed"
                ],
                "deportation_order": [
                    "Nabiloo appealed her deportation order"
                ],
                "applicable_law_or_regulation": [
                    "IRPA"
                ],
                "decision_made_by": [
                    "Federal Court",
                    "IAD"
                ]
            }
        ]
    },
    {
        "Case ID": "066240",
        "Different Crime": [
            {
                "Crime Name": "unknown",
                "Crime Type": "others",
                "procedural_fairness": [
                    "alleged violation"
                ],
                "evidence_assessment": [
                    "new evidence not considered relevant"
                ],
                "decision_reasoning": [
                    "fear found unreasonable due to lack of harm to family members"
                ],
                "standard_of_review": [
                    "reasonableness"
                ],
                "applicable_regulations": [
                    "Immigration and Refugee Protection Regulations"
                ],
                "result_of_case": [
                    "application for judicial review dismissed"
                ]
            }
        ]
    },
    {
        "Case ID": "093806",
        "Different Crime": [
            {
                "Crime Name": "Misrepresentation under Immigration and Refugee Protection Act",
                "Crime Type": "Immigration-related_Fraud_or_Misrepresentation",
                "humanitarian_and_compassionate_factors": [
                    "family reunification",
                    "best interests of a child"
                ],
                "misrepresentation_or_fraud": [
                    "concealed marriage and children"
                ],
                "decision_outcome": [
                    "unreasonable",
                    "set aside and remitted for re-determination"
                ],
                "best_interests_of_children": [
                    "not adequately addressed"
                ],
                "standard_of_review": [
                    "judicial review"
                ]
            }
        ]
    },
    {
        "Case ID": "064027",
        "Different Crime": [
            {
                "Crime Name": "Revocation of Transportation Security Clearances",
                "Crime Type": "Terrorism_or_National_Security-related_Crimes",
                "procedural_fairness": [
                    "breach of procedural fairness",
                    "insufficient disclosure",
                    "limited ability to respond effectively"
                ],
                "evidence_provided": [
                    "intelligence report",
                    "undisclosed key facts and opinions"
                ],
                "decision_outcome": [
                    "revocations set aside",
                    "remitted for redetermination"
                ],
                "judicial_review_result": [
                    "revocations overturned",
                    "case remanded for reconsideration"
                ],
                "reasoning_given": [
                    "impact on applicants' rights",
                    "nature of the decision",
                    "statutory scheme considerations"
                ],
                "legal_basis": [
                    "Aeronautics Act and related regulations"
                ]
            }
        ]
    },
    {
        "Case ID": "009663",
        "Different Crime": [
            {
                "Crime Name": "False or misleading information in personal information form (PIF)",
                "Crime Type": "Immigration-related_Fraud_or_Misrepresentation",
                "credibility_assessment": [
                    "Discrepancies in PIF led to credibility concerns"
                ],
                "evidence_assessment": [
                    "Plausible explanations for omissions ignored by Board"
                ],
                "decision_outcome": [
                    "Judicial review allowed, Board decision quashed, reconsideration ordered"
                ],
                "standard_of_review": [
                    "Reasonable explanations not addressed by Board"
                ],
                "misrepresentation_or_fraud": [
                    "False or misleading information in PIF"
                ]
            },
            {
                "Crime Name": "Bribery",
                "Crime Type": "Economic_Crimes_or_Fraud-related_Offenses",
                "procedural_fairness": [
                    "Board must address reasonable explanations",
                    "Failed to consider reasonable explanations"
                ],
                "evidence_provided": [
                    "Reasonable explanations for discrepancies",
                    "Learning of sister's illness from a friend",
                    "Family withholding police inquiries"
                ],
                "decision_outcome": [
                    "Judicial review allowed",
                    "Board's decision quashed",
                    "Reconsideration ordered"
                ],
                "judicial_authority": [
                    "Federal Court reviewed the case",
                    "Differently constituted Board ordered"
                ],
                "credibility_assessment": [
                    "Board questioned credibility based on unaddressed discrepancies"
                ],
                "appeal_outcome": [
                    "Application for judicial review was allowed"
                ]
            },
            {
                "Crime Name": "Bribery",
                "Crime Type": "Terrorism_or_National_Security-related_Crimes",
                "credibility_findings": [
                    "discrepancies in testimony",
                    "implausibility findings"
                ],
                "reasoning_given": [
                    "Board failed to consider reasonable explanations"
                ],
                "evidence_assessment": [
                    "reasonable explanations for discrepancies ignored"
                ],
                "judicial_review_result": [
                    "application allowed",
                    "decision quashed",
                    "reconsideration ordered"
                ],
                "refugee_status_claim": [
                    "fear of persecution in Pakistan"
                ],
                "decision_outcome": [
                    "case requires reconsideration by a differently constituted Board"
                ]
            }
        ]
    },
    {
        "Case ID": "027225",
        "Different Crime": [
            {
                "Crime Name": "Misrepresentation in refugee claim process",
                "Crime Type": "Immigration-related_Fraud_or_Misrepresentation",
                "legal_basis": [
                    "Section 109 of the Immigration and Refugee Protection Act"
                ],
                "misrepresentation_or_fraud": [
                    "Misrepresentation of personal information and identity"
                ],
                "procedural_fairness": [
                    "Procedural errors and lack of adequate reasoning"
                ],
                "refugee_status_eligibility": [
                    "Concerns about the validity of the refugee claim"
                ],
                "decision_outcome": [
                    "Judicial review granted, case remanded for reconsideration"
                ]
            }
        ]
    },
    {
        "Case ID": "037404",
        "Different Crime": [
            {
                "Crime Name": "Immigration Application Dispute",
                "Crime Type": "Immigration-related_Fraud_or_Misrepresentation",
                "procedural_fairness": [
                    "denied procedural fairness"
                ],
                "legal_basis": [
                    "IRPA s12(2)",
                    "Regulations s88(1)"
                ],
                "evidence_assessment": [
                    "insufficient documentation",
                    "economic contribution",
                    "relevant experience"
                ],
                "decision_outcome": [
                    "application dismissed",
                    "officer's decision upheld"
                ],
                "regulatory_compliance": [
                    "failed to meet requirements"
                ]
            }
        ]
    },
    {
        "Case ID": "007648",
        "Different Crime": [
            {
                "Crime Name": "Inadmissibility due to misrepresentation",
                "Crime Type": "Immigration-related_Fraud_or_Misrepresentation",
                "misrepresentation_or_fraud": [
                    "sons' ages"
                ],
                "evidence_assessment": [
                    "bone age tests",
                    "consistent documentation"
                ],
                "decision_outcome": [
                    "judicial review granted",
                    "case remanded for reconsideration"
                ],
                "standard_of_review": [
                    "patently unreasonable"
                ]
            }
        ]
    },
    {
        "Case ID": "015851",
        "Different Crime": [
            {
                "Crime Name": "unknown",
                "Crime Type": "others",
                "legal_basis": [
                    "Public Service Employment Act (PSEA)",
                    "Regulations"
                ],
                "standard_of_review": [
                    "reasonableness simpliciter"
                ],
                "decision_reasoning": [
                    "no formal offer was made",
                    "incomplete selection processes",
                    "lack of authority by Ms. Diotte",
                    "Ms. Dumouchel's acting appointment complied with PSEA and Regulations"
                ],
                "result_of_case": [
                    "application for judicial review is dismissed"
                ],
                "evidence_consideration": [
                    "investigator's findings under the PSEA and Regulations"
                ],
                "cause_of_action": [
                    "improper rescission of a verbal job offer"
                ]
            }
        ]
    },
    {
        "Case ID": "082652",
        "Different Crime": [
            {
                "Crime Name": "unknown",
                "Crime Type": "others",
                "legal_basis": [
                    "subsection 110(4) of the Immigration and Refugee Protection Act"
                ],
                "evidence_assessment": [
                    "diploma admissibility criteria"
                ],
                "decision_reasoning": [
                    "RAD's decision was unreasonable"
                ],
                "application_details": [
                    "RAD refused to admit a 2002 diploma"
                ],
                "result_of_case": [
                    "Judicial review granted",
                    "RAD's decision overturned",
                    "case remanded for reconsideration"
                ],
                "relevant_statute": [
                    "Immigration and Refugee Protection Act"
                ],
                "procedure_followed": [
                    "Court analyzed RAD's role, subsection 110(4), and whether the diploma met admissibility criteria"
                ],
                "cause_of_action": [
                    "applicant sought judicial review after the RAD rejected his appeal, citing improper evidence handling"
                ]
            }
        ]
    },
    {
        "Case ID": "035191",
        "Different Crime": [
            {
                "Crime Name": "Refugee Status Claim",
                "Crime Type": "Refugee_Claim-related_Issues",
                "credibility_findings": [
                    "credibility issues",
                    "reasonably assess credibility"
                ],
                "legal_basis": [
                    "subsection 108(4) of IRPA"
                ],
                "evidence_assessment": [
                    "conclusive evidence for FARC involvement",
                    "ignoring family-wide persecution"
                ],
                "risk_of_persecution": [
                    "FARC threats and violence against her family"
                ],
                "decision_outcome": [
                    "Board's decision is quashed and remitted for reconsideration"
                ],
                "review_standard": [
                    "Judicial review analyzed the Board's credibility findings and application of IRPA provisions"
                ]
            }
        ]
    },
    {
        "Case ID": "072955",
        "Different Crime": [
            {
                "Crime Name": "Discrimination complaint under the Canadian Human Rights Act",
                "Crime Type": "Human_Rights_or_International_Law_Violations",
                "time_limit": [
                    "paragraph 41(1)(e) of the Canadian Human Rights Act"
                ],
                "administrative_error": [
                    "not properly exercising its discretion",
                    "providing insufficient reasons"
                ],
                "judicial_review_process": [
                    "analyzed whether the Commission correctly applied the time limit and exercised discretion"
                ],
                "decision_outcome": [
                    "set aside",
                    "remitted for reconsideration"
                ],
                "burden_of_proof": [
                    "limitation period began in June 2004 after CIC's final decision",
                    "limitation period began in December 2001"
                ],
                "charter_rights_violation": [
                    "human rights complaint dismissed due to being filed out of time"
                ]
            }
        ]
    },
    {
        "Case ID": "078842",
        "Different Crime": [
            {
                "Crime Name": "Refugee Claim Dismissal",
                "Crime Type": "Refugee_Claim-related_Issues",
                "procedural_fairness": [
                    "violated",
                    "ignoring evidence",
                    "hostile hearing environment"
                ],
                "risk_of_persecution": [
                    "gender-based persecution",
                    "domestic violence"
                ],
                "evidence_assessment": [
                    "failed to address domestic violence evidence",
                    "inappropriate questioning of ethnicity"
                ],
                "social_group_membership": [
                    "Roma ethnicity"
                ],
                "gender_guidelines": [
                    "relevant to gender-based persecution"
                ],
                "decision_outcome": [
                    "application for judicial review granted",
                    "case remanded for reconsideration"
                ],
                "specific_vulnerabilities": [
                    "applicant and her children"
                ]
            }
        ]
    },
    {
        "Case ID": "039301",
        "Different Crime": [
            {
                "Crime Name": "Border document misrepresentation",
                "Crime Type": "Immigration-related_Fraud_or_Misrepresentation",
                "legal_basis": [
                    "IRPA sections 96 and 97"
                ],
                "standard_of_review": [
                    "reasonableness"
                ],
                "risk_assessment": [
                    "no specific risks in Colombo"
                ],
                "evidence_assessment": [
                    "no credible link between extortion and political activities post-2012"
                ],
                "refugee_status_eligibility": [
                    "denied"
                ],
                "decision_outcome": [
                    "application dismissed"
                ]
            },
            {
                "Crime Name": "Extortion",
                "Crime Type": "Economic_Crimes_or_Fraud-related_Offenses",
                "standard_of_review": [
                    "reasonableness"
                ],
                "procedural_fairness": [
                    "no_procedural_fairness_breach"
                ],
                "evidence_provided": [
                    "police_officers_sought_money_not_political_suppression"
                ],
                "decision_outcome": [
                    "application_dismissed"
                ],
                "applicable_statute": [
                    "IRPA_sections_96_and_97"
                ],
                "claim_nature": [
                    "refugee_status_due_to_extortion_and_threats_linked_to_political_activities"
                ],
                "judicial_authority": [
                    "RPD"
                ],
                "serious_criminality": [
                    "criminally_motivated_extortion_not_politically_linked"
                ]
            },
            {
                "Crime Name": "Assault",
                "Crime Type": "Violence-related_Crimes",
                "legal_basis": [
                    "reasonableness",
                    "standard of review",
                    "justification, transparency, and intelligibility"
                ],
                "risk_assessment": [
                    "extortion",
                    "threats",
                    "criminally motivated",
                    "rogue police officers",
                    "personal gain"
                ],
                "evidence_consideration": [
                    "lack of credible evidence",
                    "political persecution"
                ],
                "refugee_status_nexus": [
                    "political activities",
                    "refugee claims"
                ],
                "internal_flight_alternative": [
                    "IFA available"
                ],
                "reasonableness_of_decision": [
                    "RPD's decision was reasonable and supported by evidence"
                ],
                "procedural_fairness": [
                    "judicial review of the RPD's decision"
                ]
            }
        ]
    },
    {
        "Case ID": "009650",
        "Different Crime": [
            {
                "Crime Name": "Refugee Status Determination",
                "Crime Type": "Refugee_Claim-related_Issues",
                "legal_basis": [
                    "Immigration and Refugee Protection Act (IRPA) and Regulations"
                ],
                "risk_of_persecution": [
                    "generalized conflict rather than targeted persecution"
                ],
                "country_conditions": [
                    "conflict had ended and conditions improved in Sierra Leone"
                ],
                "decision_outcome": [
                    "application for judicial review dismissed"
                ],
                "burden_of_proof": [
                    "foreign national must demonstrate they are either a Convention refugee abroad or a member of the humanitarian-protected persons abroad class"
                ],
                "nexus_to_convention_grounds": [
                    "experiences were part of generalized conflict"
                ]
            }
        ]
    },
    {
        "Case ID": "006221",
        "Different Crime": [
            {
                "Crime Name": "Immigration Application Dispute",
                "Crime Type": "Immigration-related_Fraud_or_Misrepresentation",
                "regulatory_compliance": [
                    "subsection 75(2) of the IRPR"
                ],
                "evidence_assessment": [
                    "Avon Appliances' letter",
                    "Happy Home English School letter"
                ],
                "decision_outcome": [
                    "judicial review granted",
                    "case remitted for reconsideration"
                ],
                "standard_of_review": [
                    "reasonableness"
                ],
                "immigration_status": [
                    "permanent residence application denied"
                ]
            }
        ]
    },
    {
        "Case ID": "018723",
        "Different Crime": [
            {
                "Crime Name": "Refugee Claim Dispute",
                "Crime Type": "Refugee_Claim-related_Issues",
                "legal_basis": [
                    "refugee protection is denied if the applicant can acquire citizenship in another country without persecution risk"
                ],
                "state_protection_analysis": [
                    "South Korea grants citizenship to North Koreans but considers factors like 'will and desire' to live there and residency in third countries"
                ],
                "documentary_evidence": [
                    "evidence shows uncertainty about the applicants' eligibility for South Korean citizenship"
                ],
                "decision_outcome": [
                    "application for judicial review is allowed, case is remanded for redetermination"
                ],
                "burden_of_proof": [
                    "insufficient evidence on South Korean citizenship"
                ],
                "review_standard": [
                    "evidence reviewed on South Korean citizenship laws"
                ]
            }
        ]
    },
    {
        "Case ID": "095669",
        "Different Crime": [
            {
                "Crime Name": "Marriage Fraud",
                "Crime Type": "Immigration-related_Fraud_or_Misrepresentation",
                "legal_basis": [
                    "Immigration and Refugee Protection Act"
                ],
                "credibility_assessment": [
                    "inconsistent testimonies",
                    "lack of credible evidence"
                ],
                "evidence_assessment": [
                    "withdrawal and reinstatement of sponsorship",
                    "lack of credible evidence (e.g., photos, communication records)"
                ],
                "decision_outcome": [
                    "marriage not genuine",
                    "judicial review application dismissed"
                ],
                "standard_of_review": [
                    "reasonableness standard"
                ]
            }
        ]
    },
    {
        "Case ID": "074753",
        "Different Crime": [
            {
                "Crime Name": "Border document misrepresentation",
                "Crime Type": "Immigration-related_Fraud_or_Misrepresentation",
                "refugee_status_eligibility": [
                    "ineligible due to Article 1F(b) of the Refugee Convention"
                ],
                "criminality_inadmissibility": [
                    "serious crime conviction (murder abroad)"
                ],
                "decision_outcome": [
                    "exclusion from refugee protection"
                ],
                "standard_of_review": [
                    "judicial review of IRB decision"
                ],
                "misrepresentation_or_fraud": [
                    "document misrepresentation"
                ]
            },
            {
                "Crime Name": "Manslaughter",
                "Crime Type": "others",
                "legal_basis": [
                    "Article 1F(b)",
                    "IRPA sections 98, 101, 112"
                ],
                "exclusion_reason": [
                    "serious non-political crimes abroad"
                ],
                "decision_reasoning": [
                    "crime's seriousness",
                    "applicable law"
                ],
                "application_details": [
                    "convicted of manslaughter in Greece"
                ],
                "result_of_case": [
                    "Application for judicial review dismissed"
                ],
                "relevant_statute": [
                    "Convention under Article 1F(b)"
                ]
            }
        ]
    },
    {
        "Case ID": "090077",
        "Different Crime": [
            {
                "Crime Name": "Trademark Dispute",
                "Crime Type": "Economic_Crimes_or_Fraud-related_Offenses",
                "applicable_statute": [
                    "Trade-marks Act provisions: sections 2, 4, 30, 38, and regulations under section 28"
                ],
                "evidence_provided": [
                    "RBH's evidence insufficient for both claims"
                ],
                "decision_outcome": [
                    "Appeal dismissed"
                ],
                "standard_of_review": [
                    "reasonable and within acceptable legal outcomes"
                ],
                "distinctiveness_evaluation": [
                    "lack of distinctiveness"
                ],
                "use_in_trade": [
                    "ITPL's marks were not used as claimed"
                ]
            }
        ]
    },
    {
        "Case ID": "067782",
        "Different Crime": [
            {
                "Crime Name": "Work Permit Refusal under Immigration and Refugee Protection Regulations",
                "Crime Type": "Immigration-related_Fraud_or_Misrepresentation",
                "legal_basis": [
                    "R200(1)(b)"
                ],
                "procedural_fairness": [
                    "Judicial review analyzed officer's reasoning against legal standards and guidelines."
                ],
                "evidence_assessment": [
                    "lack of travel history, higher earnings in Canada, and better living conditions as reasons for refusal."
                ],
                "decision_outcome": [
                    "Court ordered a fresh determination by a different officer."
                ],
                "immigration_status": [
                    "Work permit refusal"
                ]
            }
        ]
    },
    {
        "Case ID": "052265",
        "Different Crime": [
            {
                "Crime Name": "Pre-Removal Risk Assessment (PRRA) Application Rejection",
                "Crime Type": "others",
                "legal_basis": [
                    "Immigration and Refugee Protection Act"
                ],
                "evidence_assessment": [
                    "past detention",
                    "torture claims",
                    "country conditions"
                ],
                "decision_reasoning": [
                    "insufficient objective evidence"
                ],
                "standard_of_review": [
                    "reviewable error"
                ],
                "result_of_case": [
                    "Application dismissed"
                ]
            }
        ]
    },
    {
        "Case ID": "079816",
        "Different Crime": [
            {
                "Crime Name": "unknown",
                "Crime Type": "others",
                "patent_validity": [
                    "invalid"
                ],
                "infringement_analysis": [
                    "obviousness",
                    "failure as a selection patent",
                    "lack of utility",
                    "insufficiency of specification",
                    "violation of section 53"
                ],
                "evidence_assessment": [
                    "routine processes",
                    "misleading data and omissions"
                ],
                "relevant_statute": [
                    "Patent Act"
                ],
                "decision_reasoning": [
                    "besylate salt development",
                    "testing several salts",
                    "no unique advantages"
                ],
                "result_of_case": [
                    "patent invalid",
                    "awarded costs"
                ]
            }
        ]
    },
    {
        "Case ID": "060179",
        "Different Crime": [
            {
                "Crime Name": "False Representation",
                "Crime Type": "Immigration-related_Fraud_or_Misrepresentation",
                "legal_basis": [
                    "Citizenship Act Section 10"
                ],
                "misrepresentation_or_fraud": [
                    "false representation",
                    "fraud"
                ],
                "evidence_assessment": [
                    "balance of probabilities"
                ],
                "decision_outcome": [
                    "summary judgment granted"
                ],
                "immigration_status": [
                    "permanent residence application"
                ],
                "material_misrepresentation": [
                    "concealing criminal charges"
                ]
            },
            {
                "Crime Name": "Knowingly Concealing Material Circumstances",
                "Crime Type": "Violence-related_Crimes",
                "legal_basis": [
                    "Section 10 of the Citizenship Act"
                ],
                "past_criminal_convictions": [
                    "Attempted homicide"
                ],
                "standard_of_proof": [
                    "Summary judgment standard"
                ],
                "risk_assessment": [
                    "Intentional misleading of authorities"
                ],
                "evidence_consideration": [
                    "False information on application"
                ],
                "procedural_fairness": [
                    "Motion for summary judgment considered"
                ]
            }
        ]
    },
    {
        "Case ID": "008572",
        "Different Crime": [
            {
                "Crime Name": "Immigration Application Denial",
                "Crime Type": "others",
                "procedural_fairness": [
                    "denied procedural fairness"
                ],
                "evidence_assessment": [
                    "request for further evidence",
                    "IFA-related information"
                ],
                "decision_reasoning": [
                    "officer error",
                    "beyond applicants' control"
                ],
                "court_ruling": [
                    "judicial review allowed",
                    "decision set aside",
                    "remitted for redetermination"
                ],
                "application_details": [
                    "H&C application refused"
                ]
            }
        ]
    },
    {
        "Case ID": "081689",
        "Different Crime": [
            {
                "Crime Name": "Providing false information in Personal Identification Form",
                "Crime Type": "Immigration-related_Fraud_or_Misrepresentation",
                "legal_basis": [
                    "IRPA s.98",
                    "Refugee Convention Art.1F(b)"
                ],
                "misrepresentation_or_fraud": [
                    "forged passport",
                    "fraudulent identity",
                    "incomplete/incorrect info in PIF"
                ],
                "decision_outcome": [
                    "RPD's exclusion decision overturned",
                    "case returned for reassessment"
                ],
                "standard_of_review": [
                    "judicial review application granted"
                ],
                "procedural_fairness": [
                    "remanded for redetermination by a different panel"
                ],
                "risk_assessment": [
                    "seriousness of offense assessed per Supreme Court guidelines"
                ],
                "document_authenticity": [
                    "use of forged passport"
                ]
            },
            {
                "Crime Name": "Shoplifting and Identity Fraud",
                "Crime Type": "Economic_Crimes_or_Fraud-related_Offenses",
                "serious_criminality": [
                    "maximum penalty of at least 10 years",
                    "nature, mode of prosecution, prescribed penalty, circumstances"
                ],
                "mitigating_factors": [
                    "ignored mitigating factors",
                    "possibility of summary conviction with lower penalties"
                ],
                "applicable_statute": [
                    "IRPA s.98",
                    "Refugee Convention Art.1F(b)"
                ],
                "judicial_authority": [
                    "RPD",
                    "Federal Court"
                ],
                "decision_outcome": [
                    "unreasonable and set aside",
                    "case remitted for reconsideration"
                ],
                "standard_of_review": [
                    "analyzing the full sentencing range and actual conduct"
                ],
                "cause_of_action": [
                    "used a forged passport and false identity",
                    "committing shoplifting offenses in the U.S."
                ],
                "procedural_fairness": [
                    "Judicial review application after RPD excluded applicant from refugee protection"
                ]
            }
        ]
    },
    {
        "Case ID": "008365",
        "Different Crime": [
            {
                "Crime Name": "unknown",
                "Crime Type": "others",
                "legal_basis": [
                    "Federal Court Act",
                    "Indian Act"
                ],
                "procedural_fairness": [
                    "procedural irregularities"
                ],
                "evidence_assessment": [
                    "participation in elections",
                    "lack of clear legal criteria"
                ],
                "decision_reasoning": [
                    "plaintiffs failed to prove defendants acted unlawfully or suffered irreparable harm"
                ],
                "result_of_case": [
                    "Application dismissed"
                ]
            }
        ]
    },
    {
        "Case ID": "046148",
        "Different Crime": [
            {
                "Crime Name": "Refugee Status Claim",
                "Crime Type": "Refugee_Claim-related_Issues",
                "legal_basis": [
                    "IRPA sections 96 and 97",
                    "IRPA section 72"
                ],
                "credibility_findings": [
                    "lacked credible evidence",
                    "undermining his claim"
                ],
                "risk_of_persecution": [
                    "claimed persecution due to Lavalas party involvement",
                    "fear of generalized violence in Haiti was deemed non-particularized"
                ],
                "country_conditions": [
                    "generalized country conditions do not qualify as Convention grounds",
                    "generalized violence in Haiti"
                ],
                "evidence_assessment": [
                    "lived in the US for 15 years without seeking asylum"
                ],
                "decision_outcome": [
                    "application for judicial review is dismissed",
                    "Court upheld the Board’s decision, dismissing the application"
                ],
                "standard_of_proof": [
                    "Board's decision was reasonable"
                ]
            }
        ]
    }
]